django_rate_limit_redis/.pypirc
django_rate_limit_redis/CHANGELOG.md
django_rate_limit_redis/README.md
django_rate_limit_redis/__init__.py
django_rate_limit_redis/admin.py
django_rate_limit_redis/apps.py
django_rate_limit_redis/core.py
django_rate_limit_redis/decorators.py
django_rate_limit_redis/img.png
django_rate_limit_redis/img_1.png
django_rate_limit_redis/models.py
django_rate_limit_redis/tests.py
django_rate_limit_redis/views.py
django_rate_limit_redis/migrations/0001_initial.py
django_rate_limit_redis/migrations/__init__.py
django_rate_limit_redis-0.0.25.dist-info/WHEEL
django_rate_limit_redis-0.0.25.dist-info/METADATA
django_rate_limit_redis-0.0.25.dist-info/RECORD
