Metadata-Version: 2.1
Name: django_rate_limit_redis
Version: 0.0.25
Summary: django_rate_limit_redis - это приложение контроля и ограничения входящих/исходящих запросов,
Author-email: Ivan Yakob <lifestep95@gmail.com>
Project-URL: Home, https://github.com/allkotraz/django-rate-limit
